jupyter_apps/__init__.py
jupyter_apps/_version.py
jupyter_apps/handlers.py
jupyter_apps/tests/__init__.py
jupyter_apps/tests/test_handlers.py
jupyter_apps-0.0.3.data/data/etc/jupyter/jupyter_notebook_config.d/jupyter_apps.json
jupyter_apps-0.0.3.data/data/etc/jupyter/jupyter_server_config.d/jupyter_apps.json
jupyter_apps-0.0.3.data/data/share/jupyter/labextensions/@datalayer/jupyter-apps/build_log.json
jupyter_apps-0.0.3.data/data/share/jupyter/labextensions/@datalayer/jupyter-apps/package.json
jupyter_apps-0.0.3.data/data/share/jupyter/labextensions/@datalayer/jupyter-apps/schemas/@datalayer/jupyter-apps/package.json.orig
jupyter_apps-0.0.3.data/data/share/jupyter/labextensions/@datalayer/jupyter-apps/schemas/@datalayer/jupyter-apps/plugin.json
jupyter_apps-0.0.3.data/data/share/jupyter/labextensions/@datalayer/jupyter-apps/static/docker_lib_index_js.20024b58be25a89a8d33.js
jupyter_apps-0.0.3.data/data/share/jupyter/labextensions/@datalayer/jupyter-apps/static/docker_lib_index_js.20024b58be25a89a8d33.js.map
jupyter_apps-0.0.3.data/data/share/jupyter/labextensions/@datalayer/jupyter-apps/static/lib_index_js.5f3c00e82100aba816c8.js
jupyter_apps-0.0.3.data/data/share/jupyter/labextensions/@datalayer/jupyter-apps/static/lib_index_js.5f3c00e82100aba816c8.js.map
jupyter_apps-0.0.3.data/data/share/jupyter/labextensions/@datalayer/jupyter-apps/static/remoteEntry.828711608fb91fe2eeb3.js
jupyter_apps-0.0.3.data/data/share/jupyter/labextensions/@datalayer/jupyter-apps/static/remoteEntry.828711608fb91fe2eeb3.js.map
jupyter_apps-0.0.3.data/data/share/jupyter/labextensions/@datalayer/jupyter-apps/static/style.js
jupyter_apps-0.0.3.data/data/share/jupyter/labextensions/@datalayer/jupyter-apps/static/style_index_js.34836df93b6685942cb4.js
jupyter_apps-0.0.3.data/data/share/jupyter/labextensions/@datalayer/jupyter-apps/static/style_index_js.34836df93b6685942cb4.js.map
jupyter_apps-0.0.3.dist-info/METADATA
jupyter_apps-0.0.3.dist-info/WHEEL
jupyter_apps-0.0.3.dist-info/licenses/LICENSE
jupyter_apps-0.0.3.dist-info/RECORD
